[
    {
        "_id": "573a1390f29313caabcd42e8",
        "plot": "A group of bandits stage a brazen train hold-up, only to find a determined posse hot on their heels.",
        "runtime": 11.0,
        "poster": "https://m.media-amazon.com/images/M/MV5BMTU3NjE5NzYtYTYyNS00MDVmLWIwYjgtMmYwYWIxZDYyNzU2XkEyXkFqcGdeQXVyNzQzNzQxNzI@._V1_SY1000_SX677_AL_.jpg",
        "title": "The Great Train Robbery",
        "fullplot": "Among the earliest existing films in American cinema - notable as the first film that presented a narrative story to tell - it depicts a group of cowboy outlaws who hold up a train and rob the passengers. They are then pursued by a Sheriff's posse. Several scenes have color included - all hand tinted.",
        "released": "1903-12-01T00:00:00.000Z",
        "rated": "TV-G",
        "awards.wins": 1,
        "awards.nominations": 0,
        "awards.text": "1 win.",
        "lastupdated": "2015-08-13 00:27:59.177000000",
        "year": "1903",
        "imdb.rating": 7.4,
        "imdb.votes": 9847.0,
        "imdb.id": 439,
        "type": "movie",
        "tomatoes.viewer.rating": 3.7,
        "tomatoes.viewer.numReviews": 2559.0,
        "tomatoes.viewer.meter": 75.0,
        "tomatoes.fresh": 6.0,
        "tomatoes.critic.rating": 7.6,
        "tomatoes.critic.numReviews": 6.0,
        "tomatoes.critic.meter": 100.0,
        "tomatoes.rotten": 0.0,
        "tomatoes.lastUpdated": "2015-08-08T19:16:10.000Z",
        "num_mflix_comments": 0,
        "genres": [
            "Short",
            "Western"
        ],
        "cast": [
            "A.C. Abadie",
            "Gilbert M. 'Broncho Billy' Anderson",
            "George Barnes",
            "Justus D. Barnes"
        ],
        "languages": [
            "English"
        ],
        "directors": [
            "Edwin S. Porter"
        ],
        "countries": [
            "USA"
        ]
    },
    {
        "_id": "573a1390f29313caabcd446f",
        "plot": "A greedy tycoon decides, on a whim, to corner the world market in wheat. This doubles the price of bread, forcing the grain's producers into charity lines and further into poverty. The film...",
        "runtime": 14.0,
        "title": "A Corner in Wheat",
        "fullplot": "A greedy tycoon decides, on a whim, to corner the world market in wheat. This doubles the price of bread, forcing the grain's producers into charity lines and further into poverty. The film continues to contrast the ironic differences between the lives of those who work to grow the wheat and the life of the man who dabbles in its sale for profit.",
        "released": "1909-12-13T00:00:00.000Z",
        "rated": "G",
        "awards.wins": 1,
        "awards.nominations": 0,
        "awards.text": "1 win.",
        "lastupdated": "2015-08-13 00:46:30.660000000",
        "year": "1909",
        "imdb.rating": 6.6,
        "imdb.votes": 1375.0,
        "imdb.id": 832,
        "type": "movie",
        "tomatoes.viewer.rating": 3.6,
        "tomatoes.viewer.numReviews": 109.0,
        "tomatoes.viewer.meter": 73.0,
        "tomatoes.lastUpdated": "2015-05-11T18:36:53.000Z",
        "num_mflix_comments": 1,
        "genres": [
            "Short",
            "Drama"
        ],
        "cast": [
            "Frank Powell",
            "Grace Henderson",
            "James Kirkwood",
            "Linda Arvidson"
        ],
        "languages": [
            "English"
        ],
        "directors": [
            "D.W. Griffith"
        ],
        "countries": [
            "USA"
        ]
    },
    {
        "_id": "573a1390f29313caabcd4803",
        "plot": "Cartoon figures announce, via comic strip balloons, that they will move - and move they do, in a wildly exaggerated style.",
        "runtime": 7.0,
        "poster": "https://m.media-amazon.com/images/M/MV5BYzg2NjNhNTctMjUxMi00ZWU4LWI3ZjYtNTI0NTQxNThjZTk2XkEyXkFqcGdeQXVyNzg5OTk2OA@@._V1_SY1000_SX677_AL_.jpg",
        "title": "Winsor McCay, the Famous Cartoonist of the N.Y. Herald and His Moving Comics",
        "fullplot": "Cartoonist Winsor McCay agrees to create a large set of drawings that will be photographed and made into a motion picture. The job requires plenty of drawing supplies, and the cartoonist must also overcome some mishaps caused by an assistant. Finally, the work is done, and everyone can see the resulting animated picture.",
        "released": "1911-04-08T00:00:00.000Z",
        "awards.wins": 1,
        "awards.nominations": 0,
        "awards.text": "1 win.",
        "lastupdated": "2015-08-29 01:09:03.030000000",
        "year": "1911",
        "imdb.rating": 7.3,
        "imdb.votes": 1034.0,
        "imdb.id": 1737,
        "type": "movie",
        "tomatoes.viewer.rating": 3.4,
        "tomatoes.viewer.numReviews": 89.0,
        "tomatoes.viewer.meter": 47.0,
        "tomatoes.lastUpdated": "2015-08-20T18:51:24.000Z",
        "num_mflix_comments": 0,
        "genres": [
            "Animation",
            "Short",
            "Comedy"
        ],
        "cast": [
            "Winsor McCay"
        ],
        "languages": [
            "English"
        ],
        "directors": [
            "Winsor McCay",
            "J. Stuart Blackton"
        ],
        "countries": [
            "USA"
        ],
        "writers": [
            "Winsor McCay (comic strip \"Little Nemo in Slumberland\")",
            "Winsor McCay (screenplay)"
        ]
    },
    {
        "_id": "573a1390f29313caabcd4eaf",
        "plot": "A woman, with the aid of her police officer sweetheart, endeavors to uncover the prostitution ring that has kidnapped her sister, and the philanthropist who secretly runs it.",
        "runtime": 88.0,
        "poster": "https://m.media-amazon.com/images/M/MV5BYzk0YWQzMGYtYTM5MC00NjM2LWE5YzYtMjgyNDVhZDg1N2YzXkEyXkFqcGdeQXVyMzE0MjY5ODA@._V1_SY1000_SX677_AL_.jpg",
        "title": "Traffic in Souls",
        "released": "1913-11-24T00:00:00.000Z",
        "rated": "TV-PG",
        "awards.wins": 1,
        "awards.nominations": 0,
        "awards.text": "1 win.",
        "lastupdated": "2015-09-15 02:07:14.247000000",
        "year": "1913",
        "imdb.rating": 6.0,
        "imdb.votes": 371.0,
        "imdb.id": 3471,
        "type": "movie",
        "tomatoes.viewer.rating": 3.0,
        "tomatoes.viewer.numReviews": 85.0,
        "tomatoes.viewer.meter": 57.0,
        "tomatoes.lastUpdated": "2015-08-10T18:33:55.000Z",
        "num_mflix_comments": 1,
        "tomatoes.dvd": "2008-08-26T00:00:00.000Z",
        "genres": [
            "Crime",
            "Drama"
        ],
        "cast": [
            "Jane Gail",
            "Ethel Grandin",
            "William H. Turner",
            "Matt Moore"
        ],
        "languages": [
            "English"
        ],
        "directors": [
            "George Loane Tucker"
        ],
        "countries": [
            "USA"
        ]
    },
    {
        "_id": "573a1390f29313caabcd50e5",
        "plot": "The cartoonist, Winsor McCay, brings the Dinosaurus back to life in the figure of his latest creation, Gertie the Dinosaur.",
        "runtime": 12.0,
        "poster": "https://m.media-amazon.com/images/M/MV5BMTQxNzI4ODQ3NF5BMl5BanBnXkFtZTgwNzY5NzMwMjE@._V1_SY1000_SX677_AL_.jpg",
        "title": "Gertie the Dinosaur",
        "fullplot": "Winsor Z. McCay bets another cartoonist that he can animate a dinosaur. So he draws a big friendly herbivore called Gertie. Then he get into his own picture. Gertie walks through the picture, eats a tree, meets her creator, and takes him carefully on her back for a ride.",
        "released": "1914-09-15T00:00:00.000Z",
        "awards.wins": 1,
        "awards.nominations": 0,
        "awards.text": "1 win.",
        "lastupdated": "2015-08-18 01:03:15.313000000",
        "year": "1914",
        "imdb.rating": 7.3,
        "imdb.votes": 1837.0,
        "imdb.id": 4008,
        "type": "movie",
        "tomatoes.viewer.rating": 3.7,
        "tomatoes.viewer.numReviews": 29.0,
        "tomatoes.lastUpdated": "2015-08-10T19:20:03.000Z",
        "num_mflix_comments": 0,
        "genres": [
            "Animation",
            "Short",
            "Comedy"
        ],
        "cast": [
            "Winsor McCay",
            "George McManus",
            "Roy L. McCardell"
        ],
        "languages": [
            "English"
        ],
        "directors": [
            "Winsor McCay"
        ],
        "countries": [
            "USA"
        ],
        "writers": [
            "Winsor McCay"
        ]
    },
    {
        "_id": "573a1390f29313caabcd516c",
        "plot": "Original advertising for the film describes it as a drama of primitive life on the shores of the North Pacific...",
        "runtime": 65.0,
        "poster": "https://m.media-amazon.com/images/M/MV5BMjE3MjAyNzM5NV5BMl5BanBnXkFtZTgwMjA5OTg5NjE@._V1_SY1000_SX677_AL_.jpg",
        "title": "In the Land of the Head Hunters",
        "released": "1914-12-07T00:00:00.000Z",
        "awards.wins": 1,
        "awards.nominations": 0,
        "awards.text": "1 win.",
        "lastupdated": "2015-09-16 12:11:37.770000000",
        "year": "1914",
        "imdb.rating": 5.8,
        "imdb.votes": 223.0,
        "imdb.id": 4150,
        "type": "movie",
        "tomatoes.viewer.rating": 2.7,
        "tomatoes.viewer.numReviews": 64.0,
        "tomatoes.viewer.meter": 18.0,
        "tomatoes.lastUpdated": "2015-08-18T19:21:12.000Z",
        "num_mflix_comments": 1,
        "tomatoes.dvd": "2000-08-15T00:00:00.000Z",
        "tomatoes.website": "http://www.milestonefilms.com/",
        "tomatoes.production": "World Film Corporation",
        "genres": [
            "Drama",
            "History"
        ],
        "cast": [
            "Stanley Hunt",
            "Sarah Constance Smith Hunt",
            "Mrs. George Walkus",
            "Paddy 'Malid"
        ],
        "languages": [
            "English"
        ],
        "directors": [
            "Edward S. Curtis"
        ],
        "countries": [
            "USA"
        ],
        "writers": [
            "Edward S. Curtis (story)"
        ]
    },
    {
        "_id": "573a1390f29313caabcd5293",
        "plot": "Young Pauline is left a lot of money when her wealthy uncle dies. However, her uncle's secretary has been named as her guardian until she marries, at which time she will officially take ...",
        "runtime": 199.0,
        "poster": "https://m.media-amazon.com/images/M/MV5BMzgxODk1Mzk2Ml5BMl5BanBnXkFtZTgwMDg0NzkwMjE@._V1_SY1000_SX677_AL_.jpg",
        "title": "The Perils of Pauline",
        "fullplot": "Young Pauline is left a lot of money when her wealthy uncle dies. However, her uncle's secretary has been named as her guardian until she marries, at which time she will officially take possession of her inheritance. Meanwhile, her \"guardian\" and his confederates constantly come up with schemes to get rid of Pauline so that he can get his hands on the money himself.",
        "released": "1914-03-23T00:00:00.000Z",
        "awards.wins": 1,
        "awards.nominations": 0,
        "awards.text": "1 win.",
        "lastupdated": "2015-09-12 00:01:18.647000000",
        "year": "1914",
        "imdb.rating": 7.6,
        "imdb.votes": 744.0,
        "imdb.id": 4465,
        "type": "movie",
        "tomatoes.viewer.rating": 2.8,
        "tomatoes.viewer.numReviews": 9.0,
        "tomatoes.lastUpdated": "2015-09-11T17:46:19.000Z",
        "num_mflix_comments": 0,
        "tomatoes.production": "Path\u00e8 Fr\u00e8res",
        "genres": [
            "Action"
        ],
        "cast": [
            "Pearl White",
            "Crane Wilbur",
            "Paul Panzer",
            "Edward Jos\u00e8"
        ],
        "languages": [
            "English"
        ],
        "directors": [
            "Louis J. Gasnier",
            "Donald MacKenzie"
        ],
        "countries": [
            "USA"
        ],
        "writers": [
            "Charles W. Goddard (screenplay)",
            "Basil Dickey (screenplay)",
            "Charles W. Goddard (novel)",
            "George B. Seitz",
            "Bertram Millhauser"
        ]
    },
    {
        "_id": "573a1390f29313caabcd56df",
        "plot": "An immigrant leaves his sweetheart in Italy to find a better life across the sea in the grimy slums of New York. They are eventually reunited and marry. But life in New York is hard and ...",
        "runtime": 78.0,
        "title": "The Italian",
        "fullplot": "An immigrant leaves his sweetheart in Italy to find a better life across the sea in the grimy slums of New York. They are eventually reunited and marry. But life in New York is hard and tragedy tarnishes their dream of a better life in the new world.",
        "released": "1915-01-01T00:00:00.000Z",
        "rated": "PASSED",
        "awards.wins": 1,
        "awards.nominations": 0,
        "awards.text": "1 win.",
        "lastupdated": "2015-07-27 00:07:43.230000000",
        "year": "1915",
        "imdb.rating": 6.4,
        "imdb.votes": 175.0,
        "imdb.id": 5557,
        "type": "movie",
        "tomatoes.viewer.rating": 4.0,
        "tomatoes.viewer.numReviews": 204.0,
        "tomatoes.viewer.meter": 60.0,
        "tomatoes.lastUpdated": "2015-07-24T19:30:02.000Z",
        "num_mflix_comments": 0,
        "tomatoes.dvd": "2008-08-26T00:00:00.000Z",
        "genres": [
            "Drama"
        ],
        "cast": [
            "George Beban",
            "Clara Williams",
            "J. Frank Burke",
            "Leo Willis"
        ],
        "languages": [
            "English"
        ],
        "directors": [
            "Reginald Barker"
        ],
        "countries": [
            "USA"
        ],
        "writers": [
            "Thomas H. Ince (story)",
            "C. Gardner Sullivan (story)"
        ]
    },
    {
        "_id": "573a1390f29313caabcd587d",
        "plot": "At 10 years old, Owens becomes a ragged orphan when his sainted mother dies. The Conways, who are next door neighbors, take Owen in, but the constant drinking by Jim soon puts Owen on the ...",
        "runtime": 72.0,
        "poster": "https://m.media-amazon.com/images/M/MV5BNDkxZGU4NmMtODJlNy00YzA2LTg4ZGMtNGFlNzAyNzcxOTM1XkEyXkFqcGdeQXVyOTM3MjcyMjI@._V1_SY1000_SX677_AL_.jpg",
        "title": "Regeneration",
        "fullplot": "At 10 years old, Owens becomes a ragged orphan when his sainted mother dies. The Conways, who are next door neighbors, take Owen in, but the constant drinking by Jim soon puts Owen on the street. By 17, Owen learns that might is right. By 25, Owen is the leader of his own gang who spend most of their time gambling and drinking. But Marie comes into the gangster area of town and everything changes for Owen as he falls for Marie. But he cannot tell her so, so he comes to her settlement to find education and inspiration. But soon, his old way of life will rise to confront him again.",
        "released": "1915-09-13T00:00:00.000Z",
        "rated": "PASSED",
        "awards.wins": 1,
        "awards.nominations": 0,
        "awards.text": "1 win.",
        "lastupdated": "2015-08-14 01:28:18.957000000",
        "year": "1915",
        "imdb.rating": 6.8,
        "imdb.votes": 626.0,
        "imdb.id": 5960,
        "type": "movie",
        "tomatoes.viewer.rating": 3.4,
        "tomatoes.viewer.numReviews": 395.0,
        "tomatoes.viewer.meter": 70.0,
        "tomatoes.fresh": 5.0,
        "tomatoes.critic.rating": 9.2,
        "tomatoes.critic.numReviews": 5.0,
        "tomatoes.critic.meter": 100.0,
        "tomatoes.rotten": 0.0,
        "tomatoes.lastUpdated": "2015-09-17T17:22:42.000Z",
        "num_mflix_comments": 1,
        "tomatoes.dvd": "2001-11-27T00:00:00.000Z",
        "tomatoes.production": "Fox Film Corporation",
        "genres": [
            "Biography",
            "Crime",
            "Drama"
        ],
        "cast": [
            "John McCann",
            "James A. Marcus",
            "Maggie Weston",
            "Harry McCoy"
        ],
        "languages": [
            "English"
        ],
        "directors": [
            "Raoul Walsh"
        ],
        "countries": [
            "USA"
        ],
        "writers": [
            "Owen Frawley Kildare (book)",
            "Raoul Walsh (adapted from the book: \"My Mamie Rose\")",
            "Carl Harbaugh (adapted from the book: \"My Mamie Rose\")"
        ]
    },
    {
        "_id": "573a1390f29313caabcd5a93",
        "plot": "Christ takes on the form of a pacifist count to end a senseless war.",
        "runtime": 78.0,
        "poster": "https://m.media-amazon.com/images/M/MV5BMjAwNTIxMjE5N15BMl5BanBnXkFtZTgwODc1Mjg1MzE@._V1_SY1000_SX677_AL_.jpg",
        "title": "Civilization",
        "fullplot": "Allegorical film about peace. A king starts a war, many of the women are against it, people are pressed into service. A count has constructed a submarine and gets the order to sink an ocean liner, that is also carrying - supposedly - ammunition for the enemy. The count refuses to fire the torpedos, and sinks the submarine. He survives, but in a limbo between death and life where he meets Jesus, who takes him over to preach peace. Naturally the king arrests him and sentences him to death for treason, but then Jesus shows him the real face of war.",
        "released": "1916-06-02T00:00:00.000Z",
        "awards.wins": 1,
        "awards.nominations": 0,
        "awards.text": "1 win.",
        "lastupdated": "2015-04-30 02:13:27.863000000",
        "year": "1916",
        "imdb.rating": 6.3,
        "imdb.votes": 162.0,
        "imdb.id": 6517,
        "type": "movie",
        "tomatoes.viewer.rating": 0.0,
        "tomatoes.viewer.numReviews": 7.0,
        "tomatoes.lastUpdated": "2015-08-07T18:42:35.000Z",
        "num_mflix_comments": 0,
        "genres": [
            "Drama"
        ],
        "cast": [
            "Howard C. Hickman",
            "Enid Markey",
            "Lola May",
            "Kate Bruce"
        ],
        "directors": [
            "Reginald Barker",
            "Thomas H. Ince",
            "Raymond B. West",
            "Walter Edwards",
            "David Hartford",
            "Jay Hunt",
            "J. Parker Read Jr."
        ],
        "countries": [
            "USA"
        ],
        "writers": [
            "C. Gardner Sullivan"
        ]
    },
    {
        "_id": "573a1390f29313caabcd5ea4",
        "plot": "A District Attorney's outspoken stand on abortion gets him in trouble with the local community.",
        "runtime": 62.0,
        "title": "Where Are My Children?",
        "fullplot": "While prosecuting a physician for the death of a client after an abortion, the district attorney discovers that his wife helped her society friends and the daughter of her maid obtain and pay for abortions from the physician (and was perhaps herself also a client.)",
        "released": "1916-05-01T00:00:00.000Z",
        "rated": "APPROVED",
        "awards.wins": 1,
        "awards.nominations": 0,
        "awards.text": "1 win.",
        "lastupdated": "2015-09-07 00:51:32.560000000",
        "year": "1916",
        "imdb.rating": 5.9,
        "imdb.votes": 247.0,
        "imdb.id": 7558,
        "type": "movie",
        "tomatoes.viewer.rating": 3.1,
        "tomatoes.viewer.numReviews": 34.0,
        "tomatoes.viewer.meter": 50.0,
        "tomatoes.lastUpdated": "2015-08-06T19:49:17.000Z",
        "num_mflix_comments": 0,
        "tomatoes.production": "MCA/Universal Pictures",
        "genres": [
            "Drama"
        ],
        "cast": [
            "Tyrone Power Sr.",
            "Helen Riaume",
            "Marie Walcamp",
            "Cora Drew"
        ],
        "languages": [
            "English"
        ],
        "directors": [
            "Phillips Smalley",
            "Lois Weber"
        ],
        "countries": [
            "USA"
        ],
        "writers": [
            "Lucy Payton (from the story by)",
            "Franklin Hall (from the story by)",
            "Lois Weber",
            "Phillips Smalley"
        ]
    },
    {
        "_id": "573a1390f29313caabcd6223",
        "plot": "Gwen's family is rich, but her parents ignore her and most of the servants push her around, so she is lonely and unhappy. Her father is concerned only with making money, and her mother ...",
        "runtime": 65.0,
        "title": "The Poor Little Rich Girl",
        "fullplot": "Gwen's family is rich, but her parents ignore her and most of the servants push her around, so she is lonely and unhappy. Her father is concerned only with making money, and her mother cares only about her social position. But one day a servant's irresponsibility creates a crisis that causes everyone to rethink what is important to them.",
        "released": "1917-03-05T00:00:00.000Z",
        "awards.wins": 1,
        "awards.nominations": 0,
        "awards.text": "1 win.",
        "lastupdated": "2015-07-27 00:11:31.387000000",
        "year": "1917",
        "imdb.rating": 6.9,
        "imdb.votes": 884.0,
        "imdb.id": 8443,
        "type": "movie",
        "tomatoes.viewer.rating": 3.9,
        "tomatoes.viewer.numReviews": 137.0,
        "tomatoes.viewer.meter": 77.0,
        "tomatoes.lastUpdated": "2015-08-21T18:00:25.000Z",
        "num_mflix_comments": 0,
        "tomatoes.production": "Artcraft",
        "genres": [
            "Comedy",
            "Drama",
            "Family"
        ],
        "cast": [
            "Mary Pickford",
            "Madlaine Traverse",
            "Charles Wellesley",
            "Gladys Fairbanks"
        ],
        "languages": [
            "English"
        ],
        "directors": [
            "Maurice Tourneur"
        ],
        "countries": [
            "USA"
        ],
        "writers": [
            "Eleanor Gates (play)",
            "Frances Marion (scenario)"
        ]
    },
    {
        "_id": "573a1390f29313caabcd6377",
        "plot": "A rich young Easterner who has always wanted to live in \"the Wild West\" plans to move to a Western town. Unknown to him, the town's \"wild\" days are long gone, and it is an orderly, ...",
        "runtime": 72.0,
        "title": "Wild and Woolly",
        "fullplot": "A rich young Easterner who has always wanted to live in \"the Wild West\" plans to move to a Western town. Unknown to him, the town's \"wild\" days are long gone, and it is an orderly, civilized place now. The townsmen, not wanting to lose a rich potential resident, contrive to make over the town to suit the young man's fantasy.",
        "released": "1917-06-24T00:00:00.000Z",
        "awards.wins": 1,
        "awards.nominations": 0,
        "awards.text": "1 win.",
        "lastupdated": "2015-06-05 00:40:35.137000000",
        "year": "1917",
        "imdb.rating": 6.9,
        "imdb.votes": 388.0,
        "imdb.id": 8775,
        "type": "movie",
        "num_mflix_comments": 0,
        "genres": [
            "Comedy",
            "Western",
            "Romance"
        ],
        "cast": [
            "Douglas Fairbanks",
            "Eileen Percy",
            "Calvert Carter",
            "Charles Stevens"
        ],
        "languages": [
            "English"
        ],
        "directors": [
            "John Emerson"
        ],
        "countries": [
            "USA"
        ],
        "writers": [
            "Horace B. Carpenter (story)",
            "John Emerson",
            "Anita Loos"
        ]
    },
    {
        "_id": "573a1390f29313caabcd63d6",
        "plot": "Two peasant children, Mytyl and Tyltyl, are led by Berylune, a fairy, to search for the Blue Bird of Happiness. Berylune gives Tyltyl a cap with a diamond setting, and when Tyltyl turns the...",
        "runtime": 75.0,
        "poster": "https://m.media-amazon.com/images/M/MV5BMjNlMThmNzItMTZlMS00YzJkLTk1MzktYzIyMzllOGFmZmRlXkEyXkFqcGdeQXVyMzE0MjY5ODA@._V1_SY1000_SX677_AL_.jpg",
        "title": "The Blue Bird",
        "fullplot": "Two peasant children, Mytyl and Tyltyl, are led by Berylune, a fairy, to search for the Blue Bird of Happiness. Berylune gives Tyltyl a cap with a diamond setting, and when Tyltyl turns the diamond, the children become aware of and conversant with the souls of a Dog and Cat, as well as of Fire, Water, Bread, Light, and other presumably inanimate things. The troupe thus sets off to find the elusive Blue Bird of Happiness.",
        "released": "1918-03-31T00:00:00.000Z",
        "awards.wins": 1,
        "awards.nominations": 0,
        "awards.text": "1 win.",
        "lastupdated": "2015-07-20 00:32:04.810000000",
        "year": "1918",
        "imdb.rating": 6.6,
        "imdb.votes": 446.0,
        "imdb.id": 8891,
        "type": "movie",
        "tomatoes.viewer.rating": 3.6,
        "tomatoes.viewer.numReviews": 607.0,
        "tomatoes.viewer.meter": 60.0,
        "tomatoes.lastUpdated": "2015-08-21T18:10:22.000Z",
        "num_mflix_comments": 0,
        "tomatoes.dvd": "2005-09-06T00:00:00.000Z",
        "genres": [
            "Fantasy"
        ],
        "cast": [
            "Tula Belle",
            "Robin Macdougall",
            "Edwin E. Reed",
            "Emma Lowry"
        ],
        "languages": [
            "English"
        ],
        "directors": [
            "Maurice Tourneur"
        ],
        "countries": [
            "USA"
        ],
        "writers": [
            "Maurice Maeterlinck (play)",
            "Charles Maigne"
        ]
    },
    {
        "_id": "573a1391f29313caabcd68d0",
        "plot": "A penniless young man tries to save an heiress from kidnappers and help her secure her inheritance.",
        "runtime": 22.0,
        "poster": "https://m.media-amazon.com/images/M/MV5BNzE1OWRlNDgtMTllNi00NTZiLWIyNTktYTk0MDY1ZWUwYTc5XkEyXkFqcGdeQXVyMjUxODE0MDY@._V1_SY1000_SX677_AL_.jpg",
        "title": "From Hand to Mouth",
        "fullplot": "As a penniless man worries about how he will manage to eat, he is joined by a young waif and her dog, who are in the same predicament. Meanwhile, across town a dishonest lawyer is working with a gang of criminals, trying to swindle an innocent young heiress out of her inheritance. As the heiress is on her way home from the lawyer's office, she notices the young man and the waif in the midst of their latest problem with the authorities, and she rescues them. Later on, the young man will have an unexpected opportunity to repay her for her kindness.",
        "released": "1919-12-28T00:00:00.000Z",
        "rated": "TV-G",
        "awards.wins": 0,
        "awards.nominations": 1,
        "awards.text": "1 nomination.",
        "lastupdated": "2015-04-17 00:16:14.220000000",
        "year": "1919",
        "imdb.rating": 7.0,
        "imdb.votes": 639.0,
        "imdb.id": 10146,
        "type": "movie",
        "tomatoes.viewer.rating": 3.3,
        "tomatoes.viewer.numReviews": 71.0,
        "tomatoes.viewer.meter": 55.0,
        "tomatoes.lastUpdated": "2015-08-21T18:45:11.000Z",
        "num_mflix_comments": 0,
        "tomatoes.production": "Path\u00e8 Exchange",
        "genres": [
            "Comedy",
            "Short",
            "Action"
        ],
        "cast": [
            "Harold Lloyd",
            "Mildred Davis",
            "'Snub' Pollard",
            "Peggy Cartwright"
        ],
        "languages": [
            "English"
        ],
        "directors": [
            "Alfred J. Goulding",
            "Hal Roach"
        ],
        "countries": [
            "USA"
        ],
        "writers": [
            "H.M. Walker (titles)"
        ]
    },
    {
        "_id": "573a1391f29313caabcd6d40",
        "plot": "A tipsy doctor encounters his patient sleepwalking on a building ledge, high above the street.",
        "runtime": 26.0,
        "poster": "https://m.media-amazon.com/images/M/MV5BODliMjc3ODctYjhlOC00MDM5LTgzNmUtMjQ1MmViNDQ0NzlhXkEyXkFqcGdeQXVyNTM3MDMyMDQ@._V1_SY1000_SX677_AL_.jpg",
        "title": "High and Dizzy",
        "fullplot": "After a long wait, a young doctor finally has a patient come to his office. She is a young woman whose father has brought her to be treated for sleep-walking, but the father becomes annoyed with the doctor, and takes his daughter away. Soon afterward, the young doctor shares in a drinking binge with another doctor who has built a still in his office. After a series of misadventures, the two of them wind up in the same hotel where the daughter and her father are staying, leading to some hazardous predicaments.",
        "released": "1920-07-11T00:00:00.000Z",
        "rated": "PASSED",
        "awards.wins": 0,
        "awards.nominations": 1,
        "awards.text": "1 nomination.",
        "lastupdated": "2015-08-11 00:35:33.717000000",
        "year": "1920",
        "imdb.rating": 7.0,
        "imdb.votes": 646.0,
        "imdb.id": 11293,
        "type": "movie",
        "tomatoes.viewer.rating": 3.4,
        "tomatoes.viewer.numReviews": 30.0,
        "tomatoes.viewer.meter": 70.0,
        "tomatoes.lastUpdated": "2015-06-27T19:17:10.000Z",
        "num_mflix_comments": 1,
        "genres": [
            "Comedy",
            "Short"
        ],
        "cast": [
            "Harold Lloyd",
            "Roy Brooks",
            "Mildred Davis",
            "Wallace Howe"
        ],
        "languages": [
            "English"
        ],
        "directors": [
            "Hal Roach"
        ],
        "countries": [
            "USA"
        ],
        "writers": [
            "Frank Terry (story)",
            "H.M. Walker (titles)"
        ]
    },
    {
        "_id": "573a1391f29313caabcd6e2a",
        "plot": "A newly wedded couple attempt to build a house with a prefabricated kit, unaware that a rival sabotaged the kit's component numbering.",
        "runtime": 25.0,
        "title": "One Week",
        "fullplot": "Buster and Sybil exit a chapel as newlyweds. Among the gifts is a portable house you easily put together in one week. It doesn't help that Buster's rival for Sybil switches the numbers on the crates containing the house parts.",
        "released": "1920-09-01T00:00:00.000Z",
        "rated": "TV-G",
        "awards.wins": 1,
        "awards.nominations": 0,
        "awards.text": "1 win.",
        "lastupdated": "2015-05-07 01:07:01.633000000",
        "year": "1920",
        "imdb.rating": 8.3,
        "imdb.votes": 3942.0,
        "imdb.id": 11541,
        "type": "movie",
        "tomatoes.viewer.rating": 4.3,
        "tomatoes.viewer.numReviews": 752.0,
        "tomatoes.viewer.meter": 91.0,
        "tomatoes.lastUpdated": "2015-09-13T18:22:19.000Z",
        "num_mflix_comments": 0,
        "genres": [
            "Short",
            "Comedy"
        ],
        "cast": [
            "Buster Keaton",
            "Sybil Seely"
        ],
        "languages": [
            "English"
        ],
        "directors": [
            "Edward F. Cline",
            "Buster Keaton"
        ],
        "countries": [
            "USA"
        ]
    },
    {
        "_id": "573a1391f29313caabcd6ea2",
        "plot": "The simple-minded son of a rich financier must find his own way in the world.",
        "runtime": 77.0,
        "poster": "https://m.media-amazon.com/images/M/MV5BZDNiODA3NzQtNTBmZS00NTM3LWJlOGMtMDg2NzFiNDU2M2M3XkEyXkFqcGdeQXVyMjUxODE0MDY@._V1_SY1000_SX677_AL_.jpg",
        "title": "The Saphead",
        "fullplot": "Nick Van Alstyne owns the Henrietta silver mine and is very rich. His son Bertie is naive and spoiled. His daughter Rose is married to shady investor Mark. Mark wrecks Bertie's wedding plans by making him take the blame for Mark's illegitimate daughter. Mark also nearly ruins the family business by selling off Henrietta stock at too low a price. Bertie, of all people, must come to the rescue on the trading floor.",
        "released": "1920-09-01T00:00:00.000Z",
        "awards.wins": 0,
        "awards.nominations": 1,
        "awards.text": "1 nomination.",
        "lastupdated": "2015-06-20 00:38:08.303000000",
        "year": "1920",
        "imdb.rating": 6.2,
        "imdb.votes": 1020.0,
        "imdb.id": 11652,
        "type": "movie",
        "tomatoes.viewer.rating": 3.3,
        "tomatoes.viewer.numReviews": 435.0,
        "tomatoes.viewer.meter": 49.0,
        "tomatoes.lastUpdated": "2015-06-23T19:23:34.000Z",
        "num_mflix_comments": 0,
        "tomatoes.dvd": "2000-01-11T00:00:00.000Z",
        "genres": [
            "Comedy"
        ],
        "cast": [
            "Edward Jobson",
            "Beulah Booker",
            "Edward Connelly",
            "Edward Alexander"
        ],
        "directors": [
            "Herbert Blach\u00e8",
            "Winchell Smith"
        ],
        "countries": [
            "USA"
        ],
        "writers": [
            "Bronson Howard (original play \"The Henrietta\")",
            "Victor Mapes (play)",
            "June Mathis (scenario)",
            "Winchell Smith (play)"
        ]
    },
    {
        "_id": "573a1391f29313caabcd6f98",
        "plot": "A romantic rivalry among members of a secret society becomes even tenser when one of the men is assigned to carry out an assassination.",
        "runtime": 75.0,
        "poster": "https://m.media-amazon.com/images/M/MV5BMTkwOTUyNDk1N15BMl5BanBnXkFtZTYwODI3MzI3._V1_SY1000_SX677_AL_.jpg",
        "title": "The Ace of Hearts",
        "fullplot": "A secret society holds a meeting to determine what to do about a powerful and dangerous man whom they have been studying closely for the past three months. They all agree that he deserves to die. Two of the members, Farallone and Forrest, are both in love with Lilith, the group's only female member. But Lilith accepts neither of them, preferring to devote herself to the group's cause. When the group meets again and deals cards to all the members, Forrest draws the ace of hearts, meaning that he will be the one to carry out the assassination. Lilith then suddenly agrees to marry him, in order to give him courage. But after their first night together, both of them begin to feel differently about what they have planned.",
        "released": "1924-04-04T00:00:00.000Z",
        "rated": "PASSED",
        "awards.wins": 0,
        "awards.nominations": 2,
        "awards.text": "2 nominations.",
        "lastupdated": "2015-07-20 00:01:29.560000000",
        "year": "1921",
        "imdb.rating": 7.0,
        "imdb.votes": 798.0,
        "imdb.id": 11904,
        "type": "movie",
        "tomatoes.viewer.rating": 3.5,
        "tomatoes.viewer.numReviews": 377.0,
        "tomatoes.viewer.meter": 68.0,
        "tomatoes.lastUpdated": "2015-04-28T19:29:23.000Z",
        "num_mflix_comments": 1,
        "genres": [
            "Crime",
            "Drama",
            "Mystery"
        ],
        "cast": [
            "Lon Chaney",
            "Leatrice Joy",
            "John Bowers",
            "Hardee Kirkland"
        ],
        "directors": [
            "Wallace Worsley"
        ],
        "countries": [
            "USA"
        ],
        "writers": [
            "Gouverneur Morris (by)",
            "Ruth Wightman (scenario)"
        ]
    },
    {
        "_id": "573a1391f29313caabcd70b4",
        "plot": "An extended family split up in France and Germany find themselves on opposing sides of the battlefield during World War I.",
        "runtime": 150.0,
        "poster": "https://m.media-amazon.com/images/M/MV5BOTU1ODQyYTctODhkNy00YWRmLWE2YzYtMTQ5ZjA3OTNiN2QyXkEyXkFqcGdeQXVyMzE0MjY5ODA@._V1_SY1000_SX677_AL_.jpg",
        "title": "The Four Horsemen of the Apocalypse",
        "fullplot": "Julio Madariaga is the Argentine patriarch of a wealthy family. He has two daughters, the elder wed to a Frenchman and the other to a German. He prefers the Frenchman and his family, especially his grandson Julio, causing jealousy from the German and his three sons. When Madariaga dies, the family splits up, each son-in-law returning to his own country. The Frenchman and his own move to Paris, where Julio becomes an artist and has an affair with an unhappily married woman, the lovely Marguerite Laurier. Her husband finds out, but before he can finalize a divorce, World War One rears its head and both sides of the family will endure great suffering in the conflict, especially since they must fight one another on the battlefield.",
        "released": "1923-03-31T00:00:00.000Z",
        "rated": "PASSED",
        "awards.wins": 1,
        "awards.nominations": 0,
        "awards.text": "1 win.",
        "lastupdated": "2015-08-24 00:59:30.430000000",
        "year": "1921",
        "imdb.rating": 7.9,
        "imdb.votes": 2475.0,
        "imdb.id": 12190,
        "type": "movie",
        "tomatoes.viewer.rating": 3.9,
        "tomatoes.viewer.numReviews": 507.0,
        "tomatoes.viewer.meter": 76.0,
        "tomatoes.lastUpdated": "2015-07-28T18:34:16.000Z",
        "num_mflix_comments": 1,
        "tomatoes.production": "Metro Pictures Corporation",
        "genres": [
            "Drama",
            "Romance",
            "War"
        ],
        "cast": [
            "Pomeroy Cannon",
            "Josef Swickard",
            "Bridgetta Clark",
            "Rudolph Valentino"
        ],
        "directors": [
            "Rex Ingram"
        ],
        "countries": [
            "USA"
        ],
        "writers": [
            "Vicente Blasco Ib\u00e8\u00e8ez (novel)",
            "June Mathis (written for the screen by)"
        ]
    }
]